ddtrace/__init__.py
ddtrace/api.py
ddtrace/compat.py
ddtrace/compat_async.py
ddtrace/context.py
ddtrace/encoding.py
ddtrace/monkey.py
ddtrace/pin.py
ddtrace/provider.py
ddtrace/sampler.py
ddtrace/span.py
ddtrace/tracer.py
ddtrace/util.py
ddtrace/writer.py
ddtrace/bootstrap/__init__.py
ddtrace/bootstrap/sitecustomize.py
ddtrace/commands/__init__.py
ddtrace/commands/ddtrace_run.py
ddtrace/contrib/__init__.py
ddtrace/contrib/util.py
ddtrace/contrib/aiobotocore/__init__.py
ddtrace/contrib/aiobotocore/patch.py
ddtrace/contrib/aiohttp/__init__.py
ddtrace/contrib/aiohttp/middlewares.py
ddtrace/contrib/aiohttp/patch.py
ddtrace/contrib/aiohttp/template.py
ddtrace/contrib/asyncio/__init__.py
ddtrace/contrib/asyncio/helpers.py
ddtrace/contrib/asyncio/provider.py
ddtrace/contrib/boto/__init__.py
ddtrace/contrib/boto/patch.py
ddtrace/contrib/botocore/__init__.py
ddtrace/contrib/botocore/patch.py
ddtrace/contrib/bottle/__init__.py
ddtrace/contrib/bottle/patch.py
ddtrace/contrib/bottle/trace.py
ddtrace/contrib/cassandra/__init__.py
ddtrace/contrib/cassandra/patch.py
ddtrace/contrib/cassandra/session.py
ddtrace/contrib/celery/__init__.py
ddtrace/contrib/celery/app.py
ddtrace/contrib/celery/patch.py
ddtrace/contrib/celery/task.py
ddtrace/contrib/celery/util.py
ddtrace/contrib/dbapi/__init__.py
ddtrace/contrib/django/__init__.py
ddtrace/contrib/django/apps.py
ddtrace/contrib/django/cache.py
ddtrace/contrib/django/conf.py
ddtrace/contrib/django/db.py
ddtrace/contrib/django/middleware.py
ddtrace/contrib/django/patch.py
ddtrace/contrib/django/templates.py
ddtrace/contrib/django/utils.py
ddtrace/contrib/elasticsearch/__init__.py
ddtrace/contrib/elasticsearch/metadata.py
ddtrace/contrib/elasticsearch/patch.py
ddtrace/contrib/elasticsearch/quantize.py
ddtrace/contrib/elasticsearch/transport.py
ddtrace/contrib/falcon/__init__.py
ddtrace/contrib/falcon/middleware.py
ddtrace/contrib/falcon/patch.py
kedo_ddtrace-0.8.5.0.dist-info/DESCRIPTION.rst
kedo_ddtrace-0.8.5.0.dist-info/METADATA
kedo_ddtrace-0.8.5.0.dist-info/RECORD
kedo_ddtrace-0.8.5.0.dist-info/WHEEL
kedo_ddtrace-0.8.5.0.dist-info/entry_points.txt
kedo_ddtrace-0.8.5.0.dist-info/metadata.json
kedo_ddtrace-0.8.5.0.dist-info/top_level.txt
